labton/__init__.py
labton/__main__.py
labton/annotation_app.py
labton/data/csv_text/labton_default_project.csv
labton/labton_backend/__init__.py
labton/labton_backend/action_handler.py
labton/labton_backend/config_file_handler.py
labton/labton_backend/connection_handler.py
labton/labton_backend/data_handler.py
labton/labton_backend/helper_funcs.py
labton/labton_backend/login_handler.py
labton/labton_ui/__init__.py
labton/labton_ui/flask_annotater_page.py
labton/labton_ui/static/jquery.min.js
labton/labton_ui/static/wget-log
labton/labton_ui/static/images/logo.png
labton/labton_ui/static/images/documentation_imgs/labton_interface_example.PNG
labton/labton_ui/static/images/documentation_imgs/labton_review_interface_example.PNG
labton/labton_ui/static/images/documentation_imgs/labton_workflow_example.PNG
labton/labton_ui/templates/annotering.html
labton/labton_ui/templates/login.html
labton/labton_ui/templates/review.html
labton-0.2.5.dist-info/LICENSE
labton-0.2.5.dist-info/METADATA
labton-0.2.5.dist-info/WHEEL
labton-0.2.5.dist-info/entry_points.txt
labton-0.2.5.dist-info/top_level.txt
labton-0.2.5.dist-info/RECORD
