Metadata-Version: 2.1
Name: labton
Version: 0.2.5
Summary: Clean minimal text-annotation tool - with buildt in control of Inter-Annotator Agreement
Home-page: https://github.com/Lantow/labton
Author: Morten Lantow
Author-email: Morten Lantow <MrLantow@gmail.com>
License: GNU GENERAL PUBLIC LICENSE
Project-URL: Homepage, https://github.com/lantow/labton
Keywords: annotation,annotation tool,text labeling,labeling tool,labeling,annotation app,labeling,app,text,NLP,active learning,prodigy
Classifier: License :: OSI Approved :: MIT License
Classifier: Programming Language :: Python
Classifier: Programming Language :: Python :: 3
Requires-Python: >=3.7
License-File: LICENSE
Requires-Dist: flask (>=2.2.2)
Requires-Dist: pyngrok (>=5.1.0)
Requires-Dist: flask-login (>=0.6.2)
Requires-Dist: pandas (>=1.3.5)
Requires-Dist: pyyaml (>=6.0)
Provides-Extra: dev
Requires-Dist: pip-tools ; extra == 'dev'
Requires-Dist: pytest ; extra == 'dev'
